	<Otds>
		...
		<Brands>
			<BookingGroup Area="GlobalArea">
				...
				<BookingParameter Field="BrandCode">
					<Value>FTI</Value>
				</BookingParameter>
			</BookingGroup>
		</Brands>
		<TravelType>
			<BookingGroup Area="GlobalArea" Source=”Product”>
				…
				<BookingParameter Field="TravelType">
                     <Value>PAUS</Value>
                </BookingParameter>
            </BookingGroup>
		</TravelType>
		...
		<Accommodation>
			...
			<SellingAccom>
				...
				<Booking>
					<BookingGroup Area="ServiceArea" Source="SellingAccom">
						<BookingParameter Field="ServiceCode">
							<Value>PMI007</Value>
						</BookingParameter>
						<BookingParameter Field="RequestCode">
							<Value>H</Value>
						</BookingParameter>
					</BookingGroup>
				</Booking>
				<Board Key="F">
					<Booking>
						<BookingGroup Area="ServiceArea" Source="SellingAccom">
							<BookingParameter Name="BoardCode" Field="ServiceFeatureCode" Index="1">
								<Value>F</Value>
							</BookingParameter>
						</BookingGroup>
					</Booking>
					...
				</Board>
				...
				<Unit Key="A12">
					...
					<SellingUnit Key="A12_F">
							<Booking>
								<BookingGroup Area="ServiceArea" Source="SellingAccom">
									<BookingParameter Field="ServiceFeatureCode" PadLength="3">
										<Value>A12</Value>
									</BookingParameter>
								</BookingGroup>
							</Booking>
							...
					</SellingUnit>
					...
				</Unit>
				...
			<SellingAccom>
			...
		</Accommodation>
		...
		<OnewayFlights>
			<OnewayFlight Key="DUSPMI">
				<Booking>
					<BookingGroup Area="ServiceArea" Source="OnewayFlight">
						<BookingParameter Field="RequestCode">
							<Value>F</Value>
						</BookingParameter>
						<BookingParameter Field="ServiceCode">
							<Value>DUS PMI</Value>
						</BookingParameter>
					</BookingGroup>
				</Booking>
				...
				<BookingClass Key="Y">
					<Booking>
						<BookingGroup Area="ServiceArea" Source="OnewayFlight">
							<BookingParameter Field="ServiceFeatureCode">
								<Value>Y</Value>
							</BookingParameter>
						</BookingGroup>
					</Booking>
					...
				</BookingClass>
				...
			</OnewayFlight>
			...
			<OnewayFlight Key="PMIDUS">
				<Booking>
					<BookingGroup Area="ServiceArea" Source="OnewayFlight">
						<BookingParameter Field="RequestCode">
							<Value>F</Value>
						</BookingParameter>
						<BookingParameter Field="ServiceCode">
							<Value>PMI DUS</Value>
						</BookingParameter>
					</BookingGroup>
				</Booking>
				...
				<BookingClass Key="Y">
					<Booking>
						<BookingGroup Area="ServiceArea" Source="OnewayFlight">
							<BookingParameter Field="ServiceFeatureCode">
								<Value>Y</Value>
							</BookingParameter>
						</BookingGroup>
					</Booking>
					...
				</BookingClass>
				...
			</OnewayFlight>
			...
		</OnewayFlights>
		...
	</<Otds>]]></programlisting><?xml version="1.0" encoding="UTF-8"?>
